README.md
setup.cfg
setup.py
test/test_account.py
test/test_account_ad_product.py
test/test_account_ad_product_service_ad_product.py
test/test_account_ad_product_service_api.py
test/test_account_ad_product_service_get_response.py
test/test_account_ad_product_service_page.py
test/test_account_ad_product_service_selector.py
test/test_account_ad_product_service_value.py
test/test_account_service_api.py
test/test_account_service_auth_type.py
test/test_account_service_auto_tagging_enabled.py
test/test_account_service_budget.py
test/test_account_service_delivery_status.py
test/test_account_service_get_response.py
test/test_account_service_include_test_account.py
test/test_account_service_is_test_account.py
test/test_account_service_limit_charge_type.py
test/test_account_service_mutate_response.py
test/test_account_service_operation.py
test/test_account_service_page.py
test/test_account_service_return_value.py
test/test_account_service_selector.py
test/test_account_service_status.py
test/test_account_service_type.py
test/test_account_service_value.py
test/test_ad_group.py
test/test_ad_group_ad.py
test/test_ad_group_ad_label.py
test/test_ad_group_ad_label_service_api.py
test/test_ad_group_ad_label_service_mutate_response.py
test/test_ad_group_ad_label_service_operation.py
test/test_ad_group_ad_label_service_return_value.py
test/test_ad_group_ad_label_service_value.py
test/test_ad_group_ad_service_ad.py
test/test_ad_group_ad_service_ad_style.py
test/test_ad_group_ad_service_ad_type.py
test/test_ad_group_ad_service_api.py
test/test_ad_group_ad_service_approval_status.py
test/test_ad_group_ad_service_banner_image_ad.py
test/test_ad_group_ad_service_banner_video_ad.py
test/test_ad_group_ad_service_bid.py
test/test_ad_group_ad_service_bidding_strategy_type.py
test/test_ad_group_ad_service_button_text.py
test/test_ad_group_ad_service_campaign_goal_filter_type.py
test/test_ad_group_ad_service_carrier_name.py
test/test_ad_group_ad_service_dynamic_ad.py
yahoo_ads_display.egg-info/PKG-INFO
yahoo_ads_display.egg-info/SOURCES.txt
yahoo_ads_display.egg-info/dependency_links.txt
yahoo_ads_display.egg-info/requires.txt
yahoo_ads_display.egg-info/top_level.txt
