Metadata-Version: 1.0
Name: yahoo-ads-display
Version: 1.0.0
Summary: Yahoo!広告 ディスプレイ広告 API リファレンス / Yahoo! Ads Display Ads API Reference
Home-page: UNKNOWN
Author: OpenAPI Generator community
Author-email: team@openapitools.org
License: UNKNOWN
Keywords: OpenAPI,OpenAPI-Generator,Yahoo!広告 ディスプレイ広告 API リファレンス / Yahoo! Ads Display Ads API Reference
Platform: UNKNOWN
